{
	"frames": {
		"goldCoin1.png": {
			"frame": {
				"x": 1,
				"y": 1,
				"w": 32,
				"h": 32
			},
			"rotated": false,
			"trimmed": false,
			"spriteSourceSize": {
				"x": 0,
				"y": 0,
				"w": 32,
				"h": 32
			},
			"sourceSize": {
				"w": 32,
				"h": 32
			}
		},
		"goldCoin2.png": {
			"frame": {
				"x": 35,
				"y": 1,
				"w": 32,
				"h": 32
			},
			"rotated": false,
			"trimmed": false,
			"spriteSourceSize": {
				"x": 0,
				"y": 0,
				"w": 32,
				"h": 32
			},
			"sourceSize": {
				"w": 32,
				"h": 32
			}
		},
		"goldCoin3.png": {
			"frame": {
				"x": 69,
				"y": 1,
				"w": 32,
				"h": 32
			},
			"rotated": false,
			"trimmed": false,
			"spriteSourceSize": {
				"x": 0,
				"y": 0,
				"w": 32,
				"h": 32
			},
			"sourceSize": {
				"w": 32,
				"h": 32
			}
		},
		"goldCoin4.png": {
			"frame": {
				"x": 1,
				"y": 35,
				"w": 32,
				"h": 32
			},
			"rotated": false,
			"trimmed": false,
			"spriteSourceSize": {
				"x": 0,
				"y": 0,
				"w": 32,
				"h": 32
			},
			"sourceSize": {
				"w": 32,
				"h": 32
			}
		},
		"goldCoin5.png": {
			"frame": {
				"x": 35,
				"y": 35,
				"w": 32,
				"h": 32
			},
			"rotated": false,
			"trimmed": false,
			"spriteSourceSize": {
				"x": 0,
				"y": 0,
				"w": 32,
				"h": 32
			},
			"sourceSize": {
				"w": 32,
				"h": 32
			}
		},
		"goldCoin6.png": {
			"frame": {
				"x": 69,
				"y": 35,
				"w": 32,
				"h": 32
			},
			"rotated": false,
			"trimmed": false,
			"spriteSourceSize": {
				"x": 0,
				"y": 0,
				"w": 32,
				"h": 32
			},
			"sourceSize": {
				"w": 32,
				"h": 32
			}
		},
		"goldCoin7.png": {
			"frame": {
				"x": 1,
				"y": 69,
				"w": 32,
				"h": 32
			},
			"rotated": false,
			"trimmed": false,
			"spriteSourceSize": {
				"x": 0,
				"y": 0,
				"w": 32,
				"h": 32
			},
			"sourceSize": {
				"w": 32,
				"h": 32
			}
		},
		"goldCoin8.png": {
			"frame": {
				"x": 35,
				"y": 69,
				"w": 32,
				"h": 32
			},
			"rotated": false,
			"trimmed": false,
			"spriteSourceSize": {
				"x": 0,
				"y": 0,
				"w": 32,
				"h": 32
			},
			"sourceSize": {
				"w": 32,
				"h": 32
			}
		},
		"goldCoin9.png": {
			"frame": {
				"x": 69,
				"y": 69,
				"w": 32,
				"h": 32
			},
			"rotated": false,
			"trimmed": false,
			"spriteSourceSize": {
				"x": 0,
				"y": 0,
				"w": 32,
				"h": 32
			},
			"sourceSize": {
				"w": 32,
				"h": 32
			}
		}
	},
	"meta": {
		"app": "http://www.codeandweb.com/texturepacker",
		"version": "1.0",
		"image": "spritesheet.png",
		"format": "RGBA8888",
		"size": {
			"w": 102,
			"h": 102
		},
		"scale": "1"
	}
}